{
    "alley": [
        {"coords": [174.6, -1008.3, 29.3], "heading": 250},
        {"coords": [289.5, -1035.2, 29.4], "heading": 180},
        {"coords": [64.8, -1005.1, 29.5], "heading": 70},
        {"coords": [-126.4, -862.5, 29.4], "heading": 340},
        {"coords": [-168.9, -1155.2, 23.8], "heading": 90}
    ],
    "parking": [
        {"coords": [215.8, -810.2, 30.7], "heading": 0},
        {"coords": [-283.1, -887.5, 31.1], "heading": 260},
        {"coords": [373.4, -1042.9, 29.4], "heading": 180},
        {"coords": [-563.2, -920.1, 23.9], "heading": 90},
        {"coords": [123.4, -1028.7, 29.3], "heading": 340}
    ],
    "industrial": [
        {"coords": [1234.5, -567.8, 32.1], "heading": 90},
        {"coords": [897.2, -2156.8, 32.4], "heading": 45},
        {"coords": [1083.7, -2012.5, 31.1], "heading": 270},
        {"coords": [798.4, -2991.2, 6.0], "heading": 180},
        {"coords": [1115.8, -3175.4, 5.9], "heading": 0}
    ],
    "residential": [
        {"coords": [-1037.2, -2733.8, 13.8], "heading": 150},
        {"coords": [1251.3, -1724.5, 54.3], "heading": 45},
        {"coords": [-171.4, -1711.5, 30.3], "heading": 315},
        {"coords": [336.8, -1776.2, 29.1], "heading": 90},
        {"coords": [-1178.5, -1775.3, 3.9], "heading": 225}
    ],
    "commercial": [
        {"coords": [24.1, -1107.5, 29.8], "heading": 160},
        {"coords": [-704.5, -904.2, 19.2], "heading": 85},
        {"coords": [-1222.8, -906.7, 12.3], "heading": 35},
        {"coords": [120.7, -219.4, 54.6], "heading": 250},
        {"coords": [435.2, -800.5, 29.5], "heading": 180}
    ],
    "rural": [
        {"coords": [2680.1, 3263.8, 55.2], "heading": 60},
        {"coords": [1692.4, 4929.3, 42.1], "heading": 145},
        {"coords": [1854.2, 3683.5, 34.3], "heading": 210},
        {"coords": [-1103.5, 2714.8, 18.8], "heading": 315},
        {"coords": [2126.7, 4784.2, 40.9], "heading": 90}
    ],
    "beach": [
        {"coords": [-1600.2, -1092.5, 13.0], "heading": 125},
        {"coords": [-1336.8, -1547.2, 4.4], "heading": 305},
        {"coords": [-1850.3, -635.8, 11.2], "heading": 230},
        {"coords": [-1472.1, -940.5, 10.2], "heading": 35},
        {"coords": [-1242.5, -1567.8, 4.2], "heading": 145}
    ],
    "dock": [
        {"coords": [1234.5, -567.8, 32.1], "heading": 90},
        {"coords": [-742.8, -1498.2, 5.0], "heading": 140},
        {"coords": [1083.7, -2512.5, 0.8], "heading": 270},
        {"coords": [1291.4, -2559.8, 1.2], "heading": 45},
        {"coords": [-284.6, -2647.3, 6.0], "heading": 180}
    ]
}
